swaytools/__init__.py
swaytools/info.py
swaytools/ipc.py
swaytools/tree.py
swaytools/winfocus.py
swaytools-0.1.2.dist-info/LICENSE
swaytools-0.1.2.dist-info/METADATA
swaytools-0.1.2.dist-info/WHEEL
swaytools-0.1.2.dist-info/entry_points.txt
swaytools-0.1.2.dist-info/top_level.txt
swaytools-0.1.2.dist-info/RECORD
