Metadata-Version: 2.1
Name: swaytools
Version: 0.1.2
Summary: Quality of life tools for sway
Author: Thayne McCombs
Maintainer: Thayne McCombs
License: GPL3
Project-URL: Repository, https://github.com/tmccombs/swaytools
Project-URL: Issues, https://github.com/tmccombs/swaytools/issues
Keywords: sway,tools,i3
Classifier: License :: OSI Approved :: GNU General Public License v3 (GPLv3)
Classifier: Operating System :: POSIX :: Linux
Classifier: Programming Language :: Python :: 3
Classifier: Topic :: Desktop Environment
Requires-Python: >=3.8
License-File: LICENSE
